delta/__init__.py
delta/debug.py
delta/delta_node.py
delta/core/__init__.py
delta/core/task.py
delta/core/strategy/__init__.py
delta/core/strategy/analytics.py
delta/core/strategy/learning.py
delta/core/strategy/merge.py
delta/core/strategy/result.py
delta/core/strategy/select.py
delta/core/strategy/strategy.py
delta/dataset/__init__.py
delta/dataset/dataframe.py
delta/dataset/dataset.py
delta/dataset/file.py
delta/pandas/__init__.py
delta/pandas/dataframe.py
delta/pandas/op_mixin.py
delta/pandas/series.py
delta/serialize/__init__.py
delta/serialize/arr.py
delta/serialize/task.py
delta/statsmodel/__init__.py
delta/statsmodel/logit.py
delta/statsmodel/mnlogit.py
delta/statsmodel/optimizer.py
delta/task/__init__.py
delta/task/analytics.py
delta/task/learning.py
delta/task/task.py
delta_task-0.8.3.dist-info/METADATA
delta_task-0.8.3.dist-info/WHEEL
delta_task-0.8.3.dist-info/top_level.txt
delta_task-0.8.3.dist-info/RECORD
