Metadata-Version: 2.1
Name: delta-task
Version: 0.8.3
Summary: delta framework
Home-page: https://github.com/delta-mpc/delta
Author: miaohong
Author-email: 73902525@qq.com
Requires-Python: >=3.6
Requires-Dist: cloudpickle (==1.6.0)
Requires-Dist: httpx (==0.23.0)
Requires-Dist: numpy (==1.22.0)
Requires-Dist: Pillow (==9.1.1)
Requires-Dist: pandas (==1.2.3)
Requires-Dist: pytest (==6.2.5)
Requires-Dist: torch (==1.8.2+cpu)
Requires-Dist: networkx (==2.7.1)
